LICENSE
MANIFEST.in
README.md
setup.py
tap_github/__init__.py
tap_github/client.py
tap_github/discover.py
tap_github/schema.py
tap_github/streams.py
tap_github/sync.py
tap_github.egg-info/PKG-INFO
tap_github.egg-info/SOURCES.txt
tap_github.egg-info/dependency_links.txt
tap_github.egg-info/entry_points.txt
tap_github.egg-info/requires.txt
tap_github.egg-info/top_level.txt
tap_github/schemas/assignees.json
tap_github/schemas/collaborators.json
tap_github/schemas/comments.json
tap_github/schemas/commit_comments.json
tap_github/schemas/commits.json
tap_github/schemas/events.json
tap_github/schemas/issue_events.json
tap_github/schemas/issue_labels.json
tap_github/schemas/issue_milestones.json
tap_github/schemas/issues.json
tap_github/schemas/pr_commits.json
tap_github/schemas/project_cards.json
tap_github/schemas/project_columns.json
tap_github/schemas/projects.json
tap_github/schemas/pull_requests.json
tap_github/schemas/releases.json
tap_github/schemas/review_comments.json
tap_github/schemas/reviews.json
tap_github/schemas/stargazers.json
tap_github/schemas/team_members.json
tap_github/schemas/team_memberships.json
tap_github/schemas/teams.json
tap_github/schemas/shared/issue_permissions.json
tap_github/schemas/shared/performed_via_github_app.json
tap_github/schemas/shared/pull_permissions.json
tap_github/schemas/shared/reactions.json
tap_github/schemas/shared/user.json
tests/test_github_all_fields.py
tests/test_github_automatic_fields.py
tests/test_github_bookmarks.py
tests/test_github_discovery.py
tests/test_github_interrupted_sync.py
tests/test_github_interrupted_sync_add_stream.py
tests/test_github_interrupted_sync_remove_stream.py
tests/test_github_pagination.py
tests/test_github_parent_child_independednt.py
tests/test_github_start_date.py
tests/test_github_sync.py