Metadata-Version: 2.1
Name: tap-github
Version: 3.3.0
Summary: Singer.io tap for extracting data from the GitHub API
Home-page: http://singer.io
Author: Stitch
License: UNKNOWN
Platform: UNKNOWN
Classifier: Programming Language :: Python :: 3 :: Only
Provides-Extra: dev
License-File: LICENSE
